pytrutankless/__init__.py
pytrutankless/api.py
pytrutankless/device.py
pytrutankless/errors.py
pytrutankless/token.py
pytrutankless-0.4.3.dist-info/LICENSE
pytrutankless-0.4.3.dist-info/METADATA
pytrutankless-0.4.3.dist-info/WHEEL
pytrutankless-0.4.3.dist-info/top_level.txt
pytrutankless-0.4.3.dist-info/RECORD
