Metadata-Version: 2.1
Name: pytrutankless
Version: 0.4.3
Summary: A Python client library for the TruTankless API
Author-email: Matt Coleman <mdcoleman001@gmail.com>
License: MIT License        
Project-URL: Homepage, https://github.com/colemamd/pytrutankless
Project-URL: Download, https://github.com/CyanBook/pytrutankless/releases/latest
Project-URL: Source Code, https://github.com/colemamd/pytrutankless
Project-URL: Bug Reports, https://github.com/colemamd/pytrutankless/issues
Project-URL: Release Notes, https://github.com/colemamd/pytrutankless/releases/)
Classifier: Development Status :: 3 - Alpha
Classifier: License :: OSI Approved :: MIT License
Classifier: Operating System :: OS Independent
Classifier: Programming Language :: Python :: 3
Classifier: Programming Language :: Python :: 3.8
Classifier: Programming Language :: Python :: 3.9
Classifier: Programming Language :: Python :: 3.10
Requires-Python: >=3.8
License-File: LICENSE
Requires-Dist: aiohttp
Provides-Extra: dev
Requires-Dist: black ; extra == 'dev'
Requires-Dist: flake8 ; extra == 'dev'
Requires-Dist: isort ; extra == 'dev'
Requires-Dist: pre-commit ; extra == 'dev'
Requires-Dist: pytest ; extra == 'dev'
Requires-Dist: pyyaml ; extra == 'dev'
Requires-Dist: yamllint ; extra == 'dev'
